pypirc/__init__.py
pypirc/cmd.py
pypirc/pypirc.py
pypirc_chappers-1.0.8.dist-info/DESCRIPTION.rst
pypirc_chappers-1.0.8.dist-info/METADATA
pypirc_chappers-1.0.8.dist-info/RECORD
pypirc_chappers-1.0.8.dist-info/WHEEL
pypirc_chappers-1.0.8.dist-info/entry_points.txt
pypirc_chappers-1.0.8.dist-info/metadata.json
pypirc_chappers-1.0.8.dist-info/top_level.txt
