Metadata-Version: 2.0
Name: pypirc-chappers
Version: 1.0.8
Summary: PyPiRC: .pypirc Manager
Home-page: https://github.com/chappers/pypirc
Author: Greg Albrecht
Author-email: gba@splunk.com
Maintainer: Chapman Siu
Maintainer-email: chapm0n.siu@gmail.com
License: Apache License 2.0
Platform: UNKNOWN
Requires-Dist: future
